filterparams/__init__.py
filterparams/binding.py
filterparams/obj.py
filterparams/parser.py
filterparams/safe_parser.py
filterparams/util.py
filterparams-1.0.2.dist-info/DESCRIPTION.rst
filterparams-1.0.2.dist-info/METADATA
filterparams-1.0.2.dist-info/RECORD
filterparams-1.0.2.dist-info/WHEEL
filterparams-1.0.2.dist-info/entry_points.txt
filterparams-1.0.2.dist-info/metadata.json
filterparams-1.0.2.dist-info/namespace_packages.txt
filterparams-1.0.2.dist-info/top_level.txt
