Metadata-Version: 2.0
Name: filterparams
Version: 1.0.2
Summary: Filterparams
Home-page: https://github.com/cbrand/python-filterparams
Author: Christoph Brand
Author-email: christoph@brand.rest
License: UNKNOWN
Download-URL: https://github.com/cbrand/python-filterparams/tarball/1.0.2
Platform: UNKNOWN
Classifier: Programming Language :: Python
Classifier: Development Status :: 4 - Beta
Classifier: Programming Language :: Python :: 2
Classifier: Programming Language :: Python :: 2.7
Classifier: Programming Language :: Python :: 3
Classifier: Programming Language :: Python :: 3.1
Classifier: Programming Language :: Python :: 3.2
Classifier: Programming Language :: Python :: 3.3
Classifier: Programming Language :: Python :: 3.4
Classifier: Programming Language :: Python :: 3.5
Classifier: License :: OSI Approved :: MIT License
Requires-Dist: Werkzeug
Requires-Dist: funcparserlib (>=0.3.6)
